zsuite/__init__.py
zsuite/backoff.py
zsuite/circuit_breaker.py
zsuite/config.py
zsuite/crypto.py
zsuite/exceptions.py
zsuite/file_operations.py
zsuite/logging.py
zsuite/yaml.py
zsuite/helpers/__init__.py
zsuite/helpers/byte_strings.py
zsuite/helpers/datetimes.py
zsuite/helpers/fuzzybool.py
zsuite-0.5.0.dist-info/LICENSE
zsuite-0.5.0.dist-info/METADATA
zsuite-0.5.0.dist-info/WHEEL
zsuite-0.5.0.dist-info/top_level.txt
zsuite-0.5.0.dist-info/RECORD
