Metadata-Version: 2.1
Name: zsuite
Version: 0.5.0
Requires-Python: >=3.10
License-File: LICENSE
Requires-Dist: tzdata
Requires-Dist: cryptography
Requires-Dist: python-dotenv
Requires-Dist: PyYAML
